MEDS_transforms/__init__.py
MEDS_transforms/__main__.py
MEDS_transforms/parser.py
MEDS_transforms/pytest_plugin.py
MEDS_transforms/runner.py
MEDS_transforms/utils.py
MEDS_transforms/compute_modes/__init__.py
MEDS_transforms/compute_modes/compute_fn.py
MEDS_transforms/compute_modes/match_revise.py
MEDS_transforms/configs/__init__.py
MEDS_transforms/configs/_main.yaml
MEDS_transforms/configs/_runner.yaml
MEDS_transforms/configs/dataset.py
MEDS_transforms/configs/pipeline.py
MEDS_transforms/configs/stage.py
MEDS_transforms/configs/utils.py
MEDS_transforms/dataframe/__init__.py
MEDS_transforms/dataframe/read_fn.py
MEDS_transforms/dataframe/types.py
MEDS_transforms/dataframe/write_fn.py
MEDS_transforms/mapreduce/__init__.py
MEDS_transforms/mapreduce/mapper.py
MEDS_transforms/mapreduce/reducer.py
MEDS_transforms/mapreduce/rwlock.py
MEDS_transforms/mapreduce/shard_iteration.py
MEDS_transforms/mapreduce/stage.py
MEDS_transforms/stages/README.md
MEDS_transforms/stages/__init__.py
MEDS_transforms/stages/base.py
MEDS_transforms/stages/discovery.py
MEDS_transforms/stages/docgen.py
MEDS_transforms/stages/examples.py
MEDS_transforms/stages/add_time_derived_measurements/README.md
MEDS_transforms/stages/add_time_derived_measurements/__init__.py
MEDS_transforms/stages/add_time_derived_measurements/add_time_derived_measurements.py
MEDS_transforms/stages/add_time_derived_measurements/age.py
MEDS_transforms/stages/add_time_derived_measurements/config.yaml
MEDS_transforms/stages/add_time_derived_measurements/time_of_day.py
MEDS_transforms/stages/add_time_derived_measurements/timeline_tokens.py
MEDS_transforms/stages/add_time_derived_measurements/utils.py
MEDS_transforms/stages/add_time_derived_measurements/examples/__init__.py
MEDS_transforms/stages/add_time_derived_measurements/examples/in_example_pipeline/__init__.py
MEDS_transforms/stages/add_time_derived_measurements/examples/in_example_pipeline/cfg.yaml
meds_transforms-0.6.1.dist-info/licenses/LICENSE
meds_transforms-0.6.1.dist-info/METADATA
meds_transforms-0.6.1.dist-info/WHEEL
meds_transforms-0.6.1.dist-info/entry_points.txt
meds_transforms-0.6.1.dist-info/top_level.txt
meds_transforms-0.6.1.dist-info/RECORD
