Metadata-Version: 2.4
Name: MEDS_transforms
Version: 0.6.1
Summary: A framework for compiling simple, mapreduce style pipelines over MEDS datasets.
Author-email: Matthew McDermott <mattmcdermott8@gmail.com>
Project-URL: Homepage, https://github.com/mmcdermott/MEDS_transforms
Project-URL: Issues, https://github.com/mmcdermott/MEDS_transforms/issues
Classifier: Programming Language :: Python :: 3
Classifier: License :: OSI Approved :: MIT License
Classifier: Operating System :: OS Independent
Requires-Python: >=3.11
License-File: LICENSE
Requires-Dist: polars~=1.30.0
Requires-Dist: pyarrow
Requires-Dist: hydra-core
Requires-Dist: numpy
Requires-Dist: meds~=0.4.0
Requires-Dist: filelock
Requires-Dist: pytest
Requires-Dist: meds_testing_helpers~=0.3.0
Requires-Dist: pretty-print-directory>=0.1.3
Provides-Extra: dev
Requires-Dist: pre-commit<4; extra == "dev"
Requires-Dist: ruff; extra == "dev"
Provides-Extra: tests
Requires-Dist: pytest-cov; extra == "tests"
Provides-Extra: local-parallelism
Requires-Dist: hydra-joblib-launcher; extra == "local-parallelism"
Provides-Extra: slurm-parallelism
Requires-Dist: hydra-submitit-launcher; extra == "slurm-parallelism"
Provides-Extra: docs
Requires-Dist: mkdocs==1.6.1; extra == "docs"
Requires-Dist: mkdocs-material==9.6.7; extra == "docs"
Requires-Dist: mkdocstrings[python,shell]==0.28.2; extra == "docs"
Requires-Dist: mkdocs-gen-files==0.5.0; extra == "docs"
Requires-Dist: mkdocs-literate-nav==0.6.1; extra == "docs"
Requires-Dist: mkdocs-section-index==0.3.9; extra == "docs"
Requires-Dist: mkdocs-git-authors-plugin==0.9.2; extra == "docs"
Requires-Dist: mkdocs-git-revision-date-localized-plugin==1.3.0; extra == "docs"
Requires-Dist: markdown-callouts; extra == "docs"
Dynamic: license-file
